LICENSE
README.md
setup.py
torch_yin.egg-info/PKG-INFO
torch_yin.egg-info/SOURCES.txt
torch_yin.egg-info/dependency_links.txt
torch_yin.egg-info/requires.txt
torch_yin.egg-info/top_level.txt
torchyin/__init__.py
torchyin/yin.py