Metadata-Version: 2.1
Name: torch-yin
Version: 0.1.2
Summary: Yin pitch estimator for PyTorch
Home-page: https://github.com/brentspell/torch-yin/
Author: Brent M. Spell
Author-email: brent@brentspell.com
License: UNKNOWN
Platform: UNKNOWN
Classifier: Programming Language :: Python :: 3
Classifier: License :: OSI Approved :: MIT License
Classifier: Operating System :: OS Independent
License-File: LICENSE
